pretty_table_printer/__init__.py
pretty_table_printer/pretty_table_printer.py
pretty_table_printer-0.5.0.dist-info/LICENSE
pretty_table_printer-0.5.0.dist-info/METADATA
pretty_table_printer-0.5.0.dist-info/WHEEL
pretty_table_printer-0.5.0.dist-info/entry_points.txt
pretty_table_printer-0.5.0.dist-info/top_level.txt
pretty_table_printer-0.5.0.dist-info/RECORD
