Metadata-Version: 2.1
Name: pretty-table-printer
Version: 0.5.0
Summary: A collection of utilities for turning lists of dicts into nicely formatted plain text tables.
Home-page: https://github.com/cfmeyers/pretty_table_printer
Author: Collin Meyers
Author-email: cfmeyers@gmail.com
License: MIT license
Keywords: pretty_table_printer
Platform: UNKNOWN
Classifier: Development Status :: 2 - Pre-Alpha
Classifier: Intended Audience :: Developers
Classifier: License :: OSI Approved :: MIT License
Classifier: Natural Language :: English
Classifier: Programming Language :: Python :: 3
Classifier: Programming Language :: Python :: 3.6
Classifier: Programming Language :: Python :: 3.7
